python_dm/__init__.py
python_dm/__version__.py
python_dm/main.py
python_dm-1.0.1.dist-info/LICENSE
python_dm-1.0.1.dist-info/METADATA
python_dm-1.0.1.dist-info/WHEEL
python_dm-1.0.1.dist-info/top_level.txt
python_dm-1.0.1.dist-info/RECORD
