Metadata-Version: 2.1
Name: python-dm
Version: 1.0.1
Summary: Dm.dll Python Wrapper.
Home-page: https://github.com/lvillis/python-dm.dll
Download-URL: https://github.com/lvillis/python-dm.dll/releases
Author: Lvillis
Author-email: lvillis@outlook.com
License: MIT
Classifier: Intended Audience :: Developers
Classifier: Natural Language :: English
Classifier: License :: OSI Approved :: MIT License
Classifier: Programming Language :: Python :: 3.6
Classifier: Programming Language :: Python :: 3.7
Classifier: Programming Language :: Python :: 3.8
Classifier: Programming Language :: Python :: 3.9
Classifier: Programming Language :: Python :: 3.10
Classifier: Programming Language :: Python :: 3.11
Classifier: Programming Language :: Python :: 3.12
License-File: LICENSE
Requires-Dist: pywin32
